{"version": "1.9", "metadata": {"language": {"name": "python", "engine": "CPython", "version": "3.10.9"}, "client": {"name": "appmap", "url": "https://github.com/applandinc/appmap-python"}, "git": {"repository": "", "branch": "f-forms-iamu", "commit": "75cc89d60679221b97395bc283cce9f98ff192c8", "status": ["M models/admin_models.py", "M models/ddex_models.py", "M models/migrations/0001_initial.py", "D models/migrations/0002_alter_clip_audio_file.py", "D models/migrations/0003_remove_song_party_song_party.py", "M models/migrations/__pycache__/0001_initial.cpython-310.pyc", "M models/migrations/__pycache__/0002_alter_clip_audio_file.cpython-310.pyc", "M models/migrations/__pycache__/0003_remove_song_party_song_party.cpython-310.pyc", "?? ../.idea/", "?? ../docs/assets/resources/INF232200812IMG.jpg", "?? ../docs/assets/resources/INF232200812_2023012404141674513888/", "?? models/migrations/0002_alter_order_release_type.py", "?? models/migrations/__pycache__/0002_alter_order_release_type.cpython-310.pyc", "?? models/migrations/__pycache__/0003_alter_order_release_type_alter_song_album.cpython-310.pyc", "?? models/migrations/__pycache__/0004_alter_song_crbt_code_alter_song_crbt_start_time_and_more.cpython-310.pyc", "?? models/migrations/__pycache__/0005_alter_order_release_type_alter_song_clip.cpython-310.pyc", "?? models/migrations/__pycache__/0006_alter_order_album_alter_order_release_type_and_more.cpython-310.pyc", "?? resource/", "?? tmp/"]}, "frameworks": [{"name": "Django", "version": "4.1.3"}], "name": "GET /djadmin/models/song/ (200) - 18:15:10.638", "timestamp": 1674670510.638922, "recorder": {"name": "record_requests"}}, "events": [{"http_server_request": {"request_method": "GET", "protocol": "HTTP/1.1", "path_info": "/djadmin/models/song/", "normalized_path_info": "/djadmin/models/song/", "mime_type": "text/plain", "headers": {"Content-Length": "", "Content-Type": "text/plain", "Host": "localhost:8000", "User-Agent": "Mozilla/5.0 (X11; Linux x86_64; rv:108.0) Gecko/20100101 Firefox/108.0", "Accept": "text/html,application/xhtml+xml,application/xml;q=0.9,image/avif,image/webp,*/*;q=0.8", "Accept-Language": "en-US,en;q=0.5", "Accept-Encoding": "gzip, deflate, br", "Referer": "http://localhost:8000/djadmin/models/song/add/", "Dnt": "1", "Connection": "keep-alive", "Cookie": "csrftoken=0gR0h60mlvvF7ligiOKyrgzMDpCbTpRv; sessionid=pbkpeca7fgy1xv4sd0fkciu5b57mb598; messages=.eJwdjcsKwjAQAH9l2XN026AXqQV_oXprS1iy29aSBxiK-PdWr8Mw0_fo3FpyclFL4VnR1MaeDT4WhR3PMGy2qn3DsLx0ug5IsrLEZ6KYRUOhn0Qn8gunWWnA9r6DC3ScJEewh-5W2Ya4_XcE3lyARVSgbN7vz2kL4XNEgziOXwI1Lkc:1pKkIg:8DrI3FnglPFqDYAblMCLHulaso5UPsdbfnblYyaKosY", "Upgrade-Insecure-Requests": "1", "Sec-Fetch-Dest": "document", "Sec-Fetch-Mode": "navigate", "Sec-Fetch-Site": "same-origin", "Sec-Fetch-User": "?1"}}, "message": [], "id": 2869, "event": "call", "thread_id": 1}, {"sql_query": {"sql": "SELECT \"django_session\".\"session_key\", \"django_session\".\"session_data\", \"django_session\".\"expire_date\" FROM \"django_session\" WHERE (\"django_session\".\"expire_date\" > '2023-01-25 18:15:10.567592' AND \"django_session\".\"session_key\" = 'pbkpeca7fgy1xv4sd0fkciu5b57mb598') LIMIT 21", "database_type": "sqlite", "server_version": "3.40.1"}, "id": 2870, "event": "call", "thread_id": 1}, {"parent_id": 2870, "elapsed": 0.0007779470033710822, "id": 2871, "event": "return", "thread_id": 1}, {"sql_query": {"sql": "SELECT \"auth_user\".\"id\", \"auth_user\".\"password\", \"auth_user\".\"last_login\", \"auth_user\".\"is_superuser\", \"auth_user\".\"username\", \"auth_user\".\"first_name\", \"auth_user\".\"last_name\", \"auth_user\".\"email\", \"auth_user\".\"is_staff\", \"auth_user\".\"is_active\", \"auth_user\".\"date_joined\" FROM \"auth_user\" WHERE \"auth_user\".\"id\" = 1 LIMIT 21", "database_type": "sqlite", "server_version": "3.40.1"}, "id": 2872, "event": "call", "thread_id": 1}, {"parent_id": 2872, "elapsed": 0.00026393699954496697, "id": 2873, "event": "return", "thread_id": 1}, {"sql_query": {"sql": "SELECT COUNT(*) AS \"__count\" FROM \"models_song\"", "database_type": "sqlite", "server_version": "3.40.1"}, "id": 2874, "event": "call", "thread_id": 1}, {"parent_id": 2874, "elapsed": 0.00029735100542893633, "id": 2875, "event": "return", "thread_id": 1}, {"sql_query": {"sql": "SELECT COUNT(*) AS \"__count\" FROM \"models_song\"", "database_type": "sqlite", "server_version": "3.40.1"}, "id": 2876, "event": "call", "thread_id": 1}, {"parent_id": 2876, "elapsed": 8.823700045468286e-05, "id": 2877, "event": "return", "thread_id": 1}, {"sql_query": {"sql": "SELECT \"models_song\".\"id\", \"models_song\".\"id_type\", \"models_song\".\"id_value\", \"models_song\".\"name\", \"models_song\".\"audio_file\", \"models_song\".\"has_crbt\", \"models_song\".\"crbt_start_time\", \"models_song\".\"crbt_code\", \"models_song\".\"has_clip\", \"models_song\".\"album_id\", \"models_song\".\"order_id\" FROM \"models_song\" ORDER BY \"models_song\".\"id\" DESC", "database_type": "sqlite", "server_version": "3.40.1"}, "id": 2878, "event": "call", "thread_id": 1}, {"parent_id": 2878, "elapsed": 0.00027798399969469756, "id": 2879, "event": "return", "thread_id": 1}, {"receiver": {"class": "django.template.base.Template", "object_id": 139670414984288, "value": "<Template template_string=\"{% extends \"admin/ba...\">"}, "path": "/home/iamu/Programs/projects/forevision_digital/forevision_digital_im/fd/lib/python3.10/site-packages/django/contrib/admin/templates/admin/change_list.html", "id": 2880, "event": "call", "thread_id": 1, "defined_class": "<templates>.HomeIamuProgramsProjectsForevision_DigitalForevision_Digital_ImFdLibPython310SitePackagesDjangoContribAdminTemplatesAdminChange_ListHtml", "method_id": "render", "static": false}, {"receiver": {"class": "django.template.base.Template", "object_id": 139670395621520, "value": "<Template template_string=\"{% load i18n %}<but...\">"}, "path": "/home/iamu/Programs/projects/forevision_digital/forevision_digital_im/fd/lib/python3.10/site-packages/django/contrib/admin/templates/admin/nav_sidebar.html", "id": 2881, "event": "call", "thread_id": 1, "defined_class": "<templates>.HomeIamuProgramsProjectsForevision_DigitalForevision_Digital_ImFdLibPython310SitePackagesDjangoContribAdminTemplatesAdminNav_SidebarHtml", "method_id": "render", "static": false}, {"receiver": {"class": "django.template.base.Template", "object_id": 139670417213616, "value": "<Template template_string=\"{% load i18n %}{% ...\">"}, "path": "/home/iamu/Programs/projects/forevision_digital/forevision_digital_im/fd/lib/python3.10/site-packages/django/contrib/admin/templates/admin/app_list.html", "id": 2882, "event": "call", "thread_id": 1, "defined_class": "<templates>.HomeIamuProgramsProjectsForevision_DigitalForevision_Digital_ImFdLibPython310SitePackagesDjangoContribAdminTemplatesAdminApp_ListHtml", "method_id": "render", "static": false}, {"parent_id": 2882, "elapsed": 0.0025975879980251193, "id": 2883, "event": "return", "thread_id": 1}, {"parent_id": 2881, "elapsed": 0.007051257001876365, "id": 2884, "event": "return", "thread_id": 1}, {"receiver": {"class": "django.template.base.Template", "object_id": 139670405754992, "value": "<Template template_string=\"{% load i18n admin_u...\">"}, "path": "/home/iamu/Programs/projects/forevision_digital/forevision_digital_im/fd/lib/python3.10/site-packages/django/contrib/admin/templates/admin/change_list_object_tools.html", "id": 2885, "event": "call", "thread_id": 1, "defined_class": "<templates>.HomeIamuProgramsProjectsForevision_DigitalForevision_Digital_ImFdLibPython310SitePackagesDjangoContribAdminTemplatesAdminChange_List_Object_ToolsHtml", "method_id": "render", "static": false}, {"parent_id": 2885, "elapsed": 0.00058841999998549, "id": 2886, "event": "return", "thread_id": 1}, {"receiver": {"class": "django.template.base.Template", "object_id": 139670395081376, "value": "<Template template_string=\"{% load i18n static ...\">"}, "path": "/home/iamu/Programs/projects/forevision_digital/forevision_digital_im/fd/lib/python3.10/site-packages/django/contrib/admin/templates/admin/search_form.html", "id": 2887, "event": "call", "thread_id": 1, "defined_class": "<templates>.HomeIamuProgramsProjectsForevision_DigitalForevision_Digital_ImFdLibPython310SitePackagesDjangoContribAdminTemplatesAdminSearch_FormHtml", "method_id": "render", "static": false}, {"parent_id": 2887, "elapsed": 0.00011266199726378545, "id": 2888, "event": "return", "thread_id": 1}, {"receiver": {"class": "django.template.base.Template", "object_id": 139670395084640, "value": "<Template template_string=\"{% load i18n %}<div...\">"}, "path": "/home/iamu/Programs/projects/forevision_digital/forevision_digital_im/fd/lib/python3.10/site-packages/django/contrib/admin/templates/admin/actions.html", "id": 2889, "event": "call", "thread_id": 1, "defined_class": "<templates>.HomeIamuProgramsProjectsForevision_DigitalForevision_Digital_ImFdLibPython310SitePackagesDjangoContribAdminTemplatesAdminActionsHtml", "method_id": "render", "static": false}, {"receiver": {"class": "django.template.base.Template", "object_id": 139670404523984, "value": "<Template template_string=\"<select name=\"{{ wid...\">"}, "path": "/home/iamu/Programs/projects/forevision_digital/forevision_digital_im/fd/lib/python3.10/site-packages/django/forms/templates/django/forms/widgets/select.html", "id": 2890, "event": "call", "thread_id": 1, "defined_class": "<templates>.HomeIamuProgramsProjectsForevision_DigitalForevision_Digital_ImFdLibPython310SitePackagesDjangoFormsTemplatesDjangoFormsWidgetsSelectHtml", "method_id": "render", "static": false}, {"receiver": {"class": "django.template.base.Template", "object_id": 139670404528448, "value": "<Template template_string=\"{% for name, value i...\">"}, "path": "/home/iamu/Programs/projects/forevision_digital/forevision_digital_im/fd/lib/python3.10/site-packages/django/forms/templates/django/forms/widgets/attrs.html", "id": 2891, "event": "call", "thread_id": 1, "defined_class": "<templates>.HomeIamuProgramsProjectsForevision_DigitalForevision_Digital_ImFdLibPython310SitePackagesDjangoFormsTemplatesDjangoFormsWidgetsAttrsHtml", "method_id": "render", "static": false}, {"parent_id": 2891, "elapsed": 0.0001775049968273379, "id": 2892, "event": "return", "thread_id": 1}, {"receiver": {"class": "django.template.base.Template", "object_id": 139670404580832, "value": "<Template template_string=\"<option value=\"{{ wi...\">"}, "path": "/home/iamu/Programs/projects/forevision_digital/forevision_digital_im/fd/lib/python3.10/site-packages/django/forms/templates/django/forms/widgets/select_option.html", "id": 2893, "event": "call", "thread_id": 1, "defined_class": "<templates>.HomeIamuProgramsProjectsForevision_DigitalForevision_Digital_ImFdLibPython310SitePackagesDjangoFormsTemplatesDjangoFormsWidgetsSelect_OptionHtml", "method_id": "render", "static": false}, {"receiver": {"class": "django.template.base.Template", "object_id": 139670404528448, "value": "<Template template_string=\"{% for name, value i...\">"}, "path": "/home/iamu/Programs/projects/forevision_digital/forevision_digital_im/fd/lib/python3.10/site-packages/django/forms/templates/django/forms/widgets/attrs.html", "id": 2894, "event": "call", "thread_id": 1, "defined_class": "<templates>.HomeIamuProgramsProjectsForevision_DigitalForevision_Digital_ImFdLibPython310SitePackagesDjangoFormsTemplatesDjangoFormsWidgetsAttrsHtml", "method_id": "render", "static": false}, {"parent_id": 2894, "elapsed": 0.0002995550021296367, "id": 2895, "event": "return", "thread_id": 1}, {"parent_id": 2893, "elapsed": 0.0005774489982286468, "id": 2896, "event": "return", "thread_id": 1}, {"receiver": {"class": "django.template.base.Template", "object_id": 139670404580832, "value": "<Template template_string=\"<option value=\"{{ wi...\">"}, "path": "/home/iamu/Programs/projects/forevision_digital/forevision_digital_im/fd/lib/python3.10/site-packages/django/forms/templates/django/forms/widgets/select_option.html", "id": 2897, "event": "call", "thread_id": 1, "defined_class": "<templates>.HomeIamuProgramsProjectsForevision_DigitalForevision_Digital_ImFdLibPython310SitePackagesDjangoFormsTemplatesDjangoFormsWidgetsSelect_OptionHtml", "method_id": "render", "static": false}, {"receiver": {"class": "django.template.base.Template", "object_id": 139670404528448, "value": "<Template template_string=\"{% for name, value i...\">"}, "path": "/home/iamu/Programs/projects/forevision_digital/forevision_digital_im/fd/lib/python3.10/site-packages/django/forms/templates/django/forms/widgets/attrs.html", "id": 2898, "event": "call", "thread_id": 1, "defined_class": "<templates>.HomeIamuProgramsProjectsForevision_DigitalForevision_Digital_ImFdLibPython310SitePackagesDjangoFormsTemplatesDjangoFormsWidgetsAttrsHtml", "method_id": "render", "static": false}, {"parent_id": 2898, "elapsed": 0.00011528700269991532, "id": 2899, "event": "return", "thread_id": 1}, {"parent_id": 2897, "elapsed": 0.0003545790023053996, "id": 2900, "event": "return", "thread_id": 1}, {"parent_id": 2890, "elapsed": 0.0017653189934208058, "id": 2901, "event": "return", "thread_id": 1}, {"receiver": {"class": "django.template.base.Template", "object_id": 139670404525520, "value": "<Template template_string=\"{% include \"django/f...\">"}, "path": "/home/iamu/Programs/projects/forevision_digital/forevision_digital_im/fd/lib/python3.10/site-packages/django/forms/templates/django/forms/widgets/hidden.html", "id": 2902, "event": "call", "thread_id": 1, "defined_class": "<templates>.HomeIamuProgramsProjectsForevision_DigitalForevision_Digital_ImFdLibPython310SitePackagesDjangoFormsTemplatesDjangoFormsWidgetsHiddenHtml", "method_id": "render", "static": false}, {"receiver": {"class": "django.template.base.Template", "object_id": 139670404582656, "value": "<Template template_string=\"<input type=\"{{ widg...\">"}, "path": "/home/iamu/Programs/projects/forevision_digital/forevision_digital_im/fd/lib/python3.10/site-packages/django/forms/templates/django/forms/widgets/input.html", "id": 2903, "event": "call", "thread_id": 1, "defined_class": "<templates>.HomeIamuProgramsProjectsForevision_DigitalForevision_Digital_ImFdLibPython310SitePackagesDjangoFormsTemplatesDjangoFormsWidgetsInputHtml", "method_id": "render", "static": false}, {"receiver": {"class": "django.template.base.Template", "object_id": 139670404528448, "value": "<Template template_string=\"{% for name, value i...\">"}, "path": "/home/iamu/Programs/projects/forevision_digital/forevision_digital_im/fd/lib/python3.10/site-packages/django/forms/templates/django/forms/widgets/attrs.html", "id": 2904, "event": "call", "thread_id": 1, "defined_class": "<templates>.HomeIamuProgramsProjectsForevision_DigitalForevision_Digital_ImFdLibPython310SitePackagesDjangoFormsTemplatesDjangoFormsWidgetsAttrsHtml", "method_id": "render", "static": false}, {"parent_id": 2904, "elapsed": 0.00022522400104207918, "id": 2905, "event": "return", "thread_id": 1}, {"parent_id": 2903, "elapsed": 0.00044295500265434384, "id": 2906, "event": "return", "thread_id": 1}, {"parent_id": 2902, "elapsed": 0.00059875899751205, "id": 2907, "event": "return", "thread_id": 1}, {"parent_id": 2889, "elapsed": 0.004389708003145643, "id": 2908, "event": "return", "thread_id": 1}, {"receiver": {"class": "django.template.base.Template", "object_id": 139670404586112, "value": "<Template template_string=\"{% include \"django/f...\">"}, "path": "/home/iamu/Programs/projects/forevision_digital/forevision_digital_im/fd/lib/python3.10/site-packages/django/forms/templates/django/forms/widgets/checkbox.html", "id": 2909, "event": "call", "thread_id": 1, "defined_class": "<templates>.HomeIamuProgramsProjectsForevision_DigitalForevision_Digital_ImFdLibPython310SitePackagesDjangoFormsTemplatesDjangoFormsWidgetsCheckboxHtml", "method_id": "render", "static": false}, {"receiver": {"class": "django.template.base.Template", "object_id": 139670404582656, "value": "<Template template_string=\"<input type=\"{{ widg...\">"}, "path": "/home/iamu/Programs/projects/forevision_digital/forevision_digital_im/fd/lib/python3.10/site-packages/django/forms/templates/django/forms/widgets/input.html", "id": 2910, "event": "call", "thread_id": 1, "defined_class": "<templates>.HomeIamuProgramsProjectsForevision_DigitalForevision_Digital_ImFdLibPython310SitePackagesDjangoFormsTemplatesDjangoFormsWidgetsInputHtml", "method_id": "render", "static": false}, {"receiver": {"class": "django.template.base.Template", "object_id": 139670404528448, "value": "<Template template_string=\"{% for name, value i...\">"}, "path": "/home/iamu/Programs/projects/forevision_digital/forevision_digital_im/fd/lib/python3.10/site-packages/django/forms/templates/django/forms/widgets/attrs.html", "id": 2911, "event": "call", "thread_id": 1, "defined_class": "<templates>.HomeIamuProgramsProjectsForevision_DigitalForevision_Digital_ImFdLibPython310SitePackagesDjangoFormsTemplatesDjangoFormsWidgetsAttrsHtml", "method_id": "render", "static": false}, {"parent_id": 2911, "elapsed": 0.0004542969982139766, "id": 2912, "event": "return", "thread_id": 1}, {"parent_id": 2910, "elapsed": 0.0006884679969516583, "id": 2913, "event": "return", "thread_id": 1}, {"parent_id": 2909, "elapsed": 0.0008508850005455315, "id": 2914, "event": "return", "thread_id": 1}, {"receiver": {"class": "django.template.base.Template", "object_id": 139670404586112, "value": "<Template template_string=\"{% include \"django/f...\">"}, "path": "/home/iamu/Programs/projects/forevision_digital/forevision_digital_im/fd/lib/python3.10/site-packages/django/forms/templates/django/forms/widgets/checkbox.html", "id": 2915, "event": "call", "thread_id": 1, "defined_class": "<templates>.HomeIamuProgramsProjectsForevision_DigitalForevision_Digital_ImFdLibPython310SitePackagesDjangoFormsTemplatesDjangoFormsWidgetsCheckboxHtml", "method_id": "render", "static": false}, {"receiver": {"class": "django.template.base.Template", "object_id": 139670404582656, "value": "<Template template_string=\"<input type=\"{{ widg...\">"}, "path": "/home/iamu/Programs/projects/forevision_digital/forevision_digital_im/fd/lib/python3.10/site-packages/django/forms/templates/django/forms/widgets/input.html", "id": 2916, "event": "call", "thread_id": 1, "defined_class": "<templates>.HomeIamuProgramsProjectsForevision_DigitalForevision_Digital_ImFdLibPython310SitePackagesDjangoFormsTemplatesDjangoFormsWidgetsInputHtml", "method_id": "render", "static": false}, {"receiver": {"class": "django.template.base.Template", "object_id": 139670404528448, "value": "<Template template_string=\"{% for name, value i...\">"}, "path": "/home/iamu/Programs/projects/forevision_digital/forevision_digital_im/fd/lib/python3.10/site-packages/django/forms/templates/django/forms/widgets/attrs.html", "id": 2917, "event": "call", "thread_id": 1, "defined_class": "<templates>.HomeIamuProgramsProjectsForevision_DigitalForevision_Digital_ImFdLibPython310SitePackagesDjangoFormsTemplatesDjangoFormsWidgetsAttrsHtml", "method_id": "render", "static": false}, {"parent_id": 2917, "elapsed": 0.0001649309997446835, "id": 2918, "event": "return", "thread_id": 1}, {"parent_id": 2916, "elapsed": 0.00034213499748148024, "id": 2919, "event": "return", "thread_id": 1}, {"parent_id": 2915, "elapsed": 0.0004653369978768751, "id": 2920, "event": "return", "thread_id": 1}, {"receiver": {"class": "django.template.base.Template", "object_id": 139670404586112, "value": "<Template template_string=\"{% include \"django/f...\">"}, "path": "/home/iamu/Programs/projects/forevision_digital/forevision_digital_im/fd/lib/python3.10/site-packages/django/forms/templates/django/forms/widgets/checkbox.html", "id": 2921, "event": "call", "thread_id": 1, "defined_class": "<templates>.HomeIamuProgramsProjectsForevision_DigitalForevision_Digital_ImFdLibPython310SitePackagesDjangoFormsTemplatesDjangoFormsWidgetsCheckboxHtml", "method_id": "render", "static": false}, {"receiver": {"class": "django.template.base.Template", "object_id": 139670404582656, "value": "<Template template_string=\"<input type=\"{{ widg...\">"}, "path": "/home/iamu/Programs/projects/forevision_digital/forevision_digital_im/fd/lib/python3.10/site-packages/django/forms/templates/django/forms/widgets/input.html", "id": 2922, "event": "call", "thread_id": 1, "defined_class": "<templates>.HomeIamuProgramsProjectsForevision_DigitalForevision_Digital_ImFdLibPython310SitePackagesDjangoFormsTemplatesDjangoFormsWidgetsInputHtml", "method_id": "render", "static": false}, {"receiver": {"class": "django.template.base.Template", "object_id": 139670404528448, "value": "<Template template_string=\"{% for name, value i...\">"}, "path": "/home/iamu/Programs/projects/forevision_digital/forevision_digital_im/fd/lib/python3.10/site-packages/django/forms/templates/django/forms/widgets/attrs.html", "id": 2923, "event": "call", "thread_id": 1, "defined_class": "<templates>.HomeIamuProgramsProjectsForevision_DigitalForevision_Digital_ImFdLibPython310SitePackagesDjangoFormsTemplatesDjangoFormsWidgetsAttrsHtml", "method_id": "render", "static": false}, {"parent_id": 2923, "elapsed": 0.00016471999697387218, "id": 2924, "event": "return", "thread_id": 1}, {"parent_id": 2922, "elapsed": 0.00036774299951503053, "id": 2925, "event": "return", "thread_id": 1}, {"parent_id": 2921, "elapsed": 0.0004949440044583753, "id": 2926, "event": "return", "thread_id": 1}, {"receiver": {"class": "django.template.base.Template", "object_id": 139670404586112, "value": "<Template template_string=\"{% include \"django/f...\">"}, "path": "/home/iamu/Programs/projects/forevision_digital/forevision_digital_im/fd/lib/python3.10/site-packages/django/forms/templates/django/forms/widgets/checkbox.html", "id": 2927, "event": "call", "thread_id": 1, "defined_class": "<templates>.HomeIamuProgramsProjectsForevision_DigitalForevision_Digital_ImFdLibPython310SitePackagesDjangoFormsTemplatesDjangoFormsWidgetsCheckboxHtml", "method_id": "render", "static": false}, {"receiver": {"class": "django.template.base.Template", "object_id": 139670404582656, "value": "<Template template_string=\"<input type=\"{{ widg...\">"}, "path": "/home/iamu/Programs/projects/forevision_digital/forevision_digital_im/fd/lib/python3.10/site-packages/django/forms/templates/django/forms/widgets/input.html", "id": 2928, "event": "call", "thread_id": 1, "defined_class": "<templates>.HomeIamuProgramsProjectsForevision_DigitalForevision_Digital_ImFdLibPython310SitePackagesDjangoFormsTemplatesDjangoFormsWidgetsInputHtml", "method_id": "render", "static": false}, {"receiver": {"class": "django.template.base.Template", "object_id": 139670404528448, "value": "<Template template_string=\"{% for name, value i...\">"}, "path": "/home/iamu/Programs/projects/forevision_digital/forevision_digital_im/fd/lib/python3.10/site-packages/django/forms/templates/django/forms/widgets/attrs.html", "id": 2929, "event": "call", "thread_id": 1, "defined_class": "<templates>.HomeIamuProgramsProjectsForevision_DigitalForevision_Digital_ImFdLibPython310SitePackagesDjangoFormsTemplatesDjangoFormsWidgetsAttrsHtml", "method_id": "render", "static": false}, {"parent_id": 2929, "elapsed": 0.00015721599629614502, "id": 2930, "event": "return", "thread_id": 1}, {"parent_id": 2928, "elapsed": 0.0003255640040151775, "id": 2931, "event": "return", "thread_id": 1}, {"parent_id": 2927, "elapsed": 0.00043838599958689883, "id": 2932, "event": "return", "thread_id": 1}, {"receiver": {"class": "django.template.base.Template", "object_id": 139670395087328, "value": "<Template template_string=\"{% load i18n %}{% i...\">"}, "path": "/home/iamu/Programs/projects/forevision_digital/forevision_digital_im/fd/lib/python3.10/site-packages/django/contrib/admin/templates/admin/change_list_results.html", "id": 2933, "event": "call", "thread_id": 1, "defined_class": "<templates>.HomeIamuProgramsProjectsForevision_DigitalForevision_Digital_ImFdLibPython310SitePackagesDjangoContribAdminTemplatesAdminChange_List_ResultsHtml", "method_id": "render", "static": false}, {"parent_id": 2933, "elapsed": 0.000505382995470427, "id": 2934, "event": "return", "thread_id": 1}, {"receiver": {"class": "django.template.base.Template", "object_id": 139670404244976, "value": "<Template template_string=\"{% load admin_list %...\">"}, "path": "/home/iamu/Programs/projects/forevision_digital/forevision_digital_im/fd/lib/python3.10/site-packages/django/contrib/admin/templates/admin/pagination.html", "id": 2935, "event": "call", "thread_id": 1, "defined_class": "<templates>.HomeIamuProgramsProjectsForevision_DigitalForevision_Digital_ImFdLibPython310SitePackagesDjangoContribAdminTemplatesAdminPaginationHtml", "method_id": "render", "static": false}, {"parent_id": 2935, "elapsed": 0.00026568099565338343, "id": 2936, "event": "return", "thread_id": 1}, {"parent_id": 2880, "elapsed": 0.04960073700203793, "id": 2937, "event": "return", "thread_id": 1}, {"http_server_response": {"status_code": 200, "mime_type": "text/html; charset=utf-8", "headers": {"Content-Type": "text/html; charset=utf-8", "Expires": "Wed, 25 Jan 2023 18:15:10 GMT", "Cache-Control": "max-age=0, no-cache, no-store, must-revalidate, private", "Vary": "Cookie", "X-Frame-Options": "DENY", "Content-Length": "8861", "X-Content-Type-Options": "nosniff", "Referrer-Policy": "same-origin", "Cross-Origin-Opener-Policy": "same-origin"}}, "parent_id": 2869, "elapsed": 0.07250961700628977, "id": 2938, "event": "return", "thread_id": 1}], "classMap": []}